rebalance/__init__.py
rebalance/_version.py
rebalance/bot.py
kraken_rebalance_bot-1.0.0.dist-info/LICENSE
kraken_rebalance_bot-1.0.0.dist-info/METADATA
kraken_rebalance_bot-1.0.0.dist-info/WHEEL
kraken_rebalance_bot-1.0.0.dist-info/entry_points.txt
kraken_rebalance_bot-1.0.0.dist-info/top_level.txt
kraken_rebalance_bot-1.0.0.dist-info/RECORD
