Metadata-Version: 2.1
Name: kraken-rebalance-bot
Version: 1.0.0
Summary: A rebalance trading bot for the Kraken cryptocurrency exchange.
Author-email: Benjamin Thomas Schwertfeger <contact@b-schwertfeger.de>
License: GNU GENERAL PUBLIC LICENSE
Project-URL: Homepage, https://github.com/btschwertfeger/Kraken-Rebalance-Bot
Project-URL: Bug Tracker, https://github.com/btschwertfeger/Kraken-Rebalance-Bot/issues
Keywords: crypto,trading,kraken,exchange,api
Classifier: License :: OSI Approved :: GNU General Public License v3 (GPLv3)
Classifier: Development Status :: 5 - Production/Stable
Classifier: Intended Audience :: Developers
Classifier: Topic :: Office/Business :: Financial
Classifier: Topic :: Software Development :: Libraries :: Python Modules
Classifier: Topic :: Internet :: WWW/HTTP
Classifier: Topic :: Utilities
Classifier: Programming Language :: Python
Classifier: Programming Language :: Python :: 3.11
Classifier: Framework :: AsyncIO
Classifier: Natural Language :: English
Classifier: Operating System :: MacOS
Classifier: Operating System :: Unix
Requires-Python: >=3.11
License-File: LICENSE
Requires-Dist: python-kraken-sdk (>=1.3.0)
Requires-Dist: schedule
Requires-Dist: requests
Provides-Extra: dev
Requires-Dist: build ; extra == 'dev'
Requires-Dist: black ; extra == 'dev'
Requires-Dist: mypy ; extra == 'dev'
Requires-Dist: types-requests ; extra == 'dev'
